setup.cfg
setup.py
oncodrivefm/__init__.py
oncodrivefm/analysis.py
oncodrivefm/mapping.py
oncodrivefm/matrix.py
oncodrivefm/tdm.py
oncodrivefm.egg-info/PKG-INFO
oncodrivefm.egg-info/SOURCES.txt
oncodrivefm.egg-info/dependency_links.txt
oncodrivefm.egg-info/entry_points.txt
oncodrivefm.egg-info/requires.txt
oncodrivefm.egg-info/top_level.txt
oncodrivefm/command/__init__.py
oncodrivefm/command/base.py
oncodrivefm/command/combine.py
oncodrivefm/command/compute.py
oncodrivefm/command/full.py
oncodrivefm/method/__init__.py
oncodrivefm/method/base.py
oncodrivefm/method/empirical.py
oncodrivefm/method/factory.py
oncodrivefm/method/zscore.py
oncodrivefm/utils/__init__.py
oncodrivefm/utils/labelfilter.py
oncodrivefm/utils/tsv.py