Metadata-Version: 1.1
Name: oncodrivefm
Version: 1.0.1
Summary: OncodriveFM
Home-page: https://bitbucket.org/bbglab/oncodrivefm
Author: Barcelona Biomedical Genomics research group
Author-email: nuria.lopez@upf.edu
License: UPF Free Source Code
Download-URL: https://bitbucket.org/bbglab/oncodrivefm/get/1.0.1.tar.gz
Platform: UNKNOWN
Classifier: Development Status :: 5 - Production/Stable
Classifier: Environment :: Console
Classifier: Intended Audience :: Science/Research
Classifier: Natural Language :: English
Classifier: Operating System :: OS Independent
Classifier: Programming Language :: Python
Classifier: Programming Language :: Python :: 3.4
Classifier: Topic :: Scientific/Engineering
Classifier: Topic :: Scientific/Engineering :: Bio-Informatics
